foreman_mcp_server/__init__.py
foreman_mcp_server/server.py
foreman_mcp_server-0.4.1.dist-info/LICENSE
foreman_mcp_server-0.4.1.dist-info/METADATA
foreman_mcp_server-0.4.1.dist-info/WHEEL
foreman_mcp_server-0.4.1.dist-info/entry_points.txt
foreman_mcp_server-0.4.1.dist-info/top_level.txt
foreman_mcp_server-0.4.1.dist-info/RECORD
