Metadata-Version: 2.1
Name: foreman-mcp-server
Version: 0.4.1
Summary: MCP server for Foreman host management and infrastructure automation
Author-email: Rory McMahon <rory.mcmahon@vocus.com.au>
License: MIT
Project-URL: Homepage, https://github.com/rorymcmahon/foreman-mcp-server
Project-URL: Repository, https://github.com/rorymcmahon/foreman-mcp-server
Project-URL: Issues, https://github.com/rorymcmahon/foreman-mcp-server/issues
Keywords: mcp,foreman,infrastructure,automation
Classifier: Development Status :: 4 - Beta
Classifier: Intended Audience :: Developers
Classifier: License :: OSI Approved :: MIT License
Classifier: Programming Language :: Python :: 3
Classifier: Programming Language :: Python :: 3.8
Classifier: Programming Language :: Python :: 3.9
Classifier: Programming Language :: Python :: 3.10
Classifier: Programming Language :: Python :: 3.11
Classifier: Programming Language :: Python :: 3.12
Requires-Python: >=3.8
License-File: LICENSE
Requires-Dist: mcp>=1.0.0
Requires-Dist: requests>=2.25.0
Provides-Extra: dev
Requires-Dist: pytest>=7.0.0; extra == "dev"
Requires-Dist: pytest-asyncio>=0.21.0; extra == "dev"
Requires-Dist: black>=22.0.0; extra == "dev"
Requires-Dist: isort>=5.0.0; extra == "dev"
Requires-Dist: mypy>=1.0.0; extra == "dev"
Requires-Dist: build>=0.10.0; extra == "dev"
Requires-Dist: twine>=4.0.0; extra == "dev"
